stravaweblib/__init__.py
stravaweblib/webclient.py
stravaweblib-0.0.10.dist-info/METADATA
stravaweblib-0.0.10.dist-info/WHEEL
stravaweblib-0.0.10.dist-info/top_level.txt
stravaweblib-0.0.10.dist-info/RECORD
